{
    "blank": {
        "key": "blank",
        "label": "Page vierge",
        "thumb": null,
        "layout": {
            "rows": []
        }
    },
    "template1": {
        "key": "template1",
        "label": "Compact",
        "thumb": "/templates/t1.png",
        "layout": {
            "rows": [
                [
                    {
                        "id": "s1",
                        "type": "Identité",
                        "width": 200,
                        "isCollapsed": false
                    },
                    {
                        "id": "s2",
                        "type": "Contact",
                        "width": 200,
                        "isCollapsed": false
                    },
                    {
                        "id": "s3",
                        "type": "Lore",
                        "width": 400,
                        "isCollapsed": false
                    },
                    {
                        "id": "s4",
                        "type": "Quêtes",
                        "width": 400,
                        "isCollapsed": false
                    },
                    {
                        "id": "s5",
                        "type": "NewbiePark",
                        "width": 400,
                        "isCollapsed": false
                    }
                ],
                [
                    {
                        "id": "s6",
                        "type": "empty",
                        "width": 350
                    },
                    {
                        "id": "s7",
                        "type": "HautsFaits",
                        "width": 400,
                        "isCollapsed": false
                    },
                    {
                        "id": "s8",
                        "type": "Talents",
                        "width": 400,
                        "isCollapsed": false
                    },
                    {
                        "id": "s9",
                        "type": "Qualités",
                        "width": 400,
                        "isCollapsed": false
                    },
                    {
                        "id": "s10",
                        "type": "empty",
                        "width": 350
                    }
                ],
                [
                    {
                        "id": "s11",
                        "type": "empty",
                        "width": 400
                    },
                    {
                        "id": "s12",
                        "type": "Langues",
                        "width": 200,
                        "isCollapsed": false
                    },
                    {
                        "id": "s13",
                        "type": "empty",
                        "width": 200
                    },
                    {
                        "id": "s14",
                        "type": "Hobbies",
                        "width": 200,
                        "isCollapsed": false
                    },
                    {
                        "id": "s15",
                        "type": "empty",
                        "width": 400
                    }
                ]
            ]
        }
    },
    "template2": {
        "key": "template2",
        "label": "Aéré",
        "thumb": "/templates/t2.png",
        "layout": {
            "rows": [
                [
                    {
                        "id": "s1",
                        "type": "Identité",
                        "width": 300,
                        "isCollapsed": false
                    },
                    {
                        "id": "s2",
                        "type": "Lore",
                        "width": 400,
                        "isCollapsed": false
                    },
                    {
                        "id": "s3",
                        "type": "empty",
                        "width": 200
                    },
                    {
                        "id": "s4",
                        "type": "NewbiePark",
                        "width": 400,
                        "isCollapsed": false
                    },
                    {
                        "id": "s5",
                        "type": "Qualités",
                        "width": 400,
                        "isCollapsed": false
                    }
                ],
                [
                    {
                        "id": "s6",
                        "type": "HautsFaits",
                        "width": 400,
                        "isCollapsed": false
                    },
                    {
                        "id": "s7",
                        "type": "empty",
                        "width": 300
                    },
                    {
                        "id": "s8",
                        "type": "Quêtes",
                        "width": 400,
                        "isCollapsed": false
                    },
                    {
                        "id": "s9",
                        "type": "empty",
                        "width": 300
                    },
                    {
                        "id": "s10",
                        "type": "Talents",
                        "width": 400,
                        "isCollapsed": false
                    }
                ],
                [
                    {
                        "id": "s11",
                        "type": "empty",
                        "width": 400
                    },
                    {
                        "id": "s12",
                        "type": "Langues",
                        "width": 300,
                        "isCollapsed": false
                    },
                    {
                        "id": "s13",
                        "type": "empty",
                        "width": 300
                    },
                    {
                        "id": "s14",
                        "type": "Hobbies",
                        "width": 400,
                        "isCollapsed": false
                    },
                    {
                        "id": "s15",
                        "type": "empty",
                        "width": 400
                    }
                ]
            ]
        }
    },
    "template3": {
        "key": "template3",
        "label": "Condensé",
        "thumb": "/templates/t3.png",
        "layout": {
            "rows": [
                [
                    {
                        "id": "s1",
                        "type": "empty",
                        "width": 380,
                        "isCollapsed": false
                    },
                    {
                        "id": "s2",
                        "type": "Lore",
                        "width": 400,
                        "isCollapsed": false
                    },
                    {
                        "id": "s3",
                        "type": "NewbiePark",
                        "width": 400,
                        "isCollapsed": false
                    },
                    {
                        "id": "s4",
                        "type": "HautsFaits",
                        "width": 400,
                        "isCollapsed": false
                    },
                    {
                        "id": "s5",
                        "type": "empty",
                        "width": 380
                    }
                ],
                [
                    {
                        "id": "s6",
                        "type": "empty",
                        "width": 360
                    },
                    {
                        "id": "s7",
                        "type": "Quêtes",
                        "width": 400,
                        "isCollapsed": false
                    },
                    {
                        "id": "s8",
                        "type": "empty",
                        "width": 400,
                        "isCollapsed": false
                    },
                    {
                        "id": "s9",
                        "type": "Talents",
                        "width": 400,
                        "isCollapsed": false
                    },
                    {
                        "id": "s10",
                        "type": "empty",
                        "width": 360
                    }
                ],
                [
                    {
                        "id": "s11",
                        "type": "empty",
                        "width": 380
                    },
                    {
                        "id": "s12",
                        "type": "Qualités",
                        "width": 400,
                        "isCollapsed": false
                    },
                    {
                        "id": "s13",
                        "type": "Hobbies",
                        "width": 400,
                        "isCollapsed": false
                    },
                    {
                        "id": "s14",
                        "type": "Langues",
                        "width": 400,
                        "isCollapsed": false
                    },
                    {
                        "id": "s15",
                        "type": "empty",
                        "width": 380
                    }
                ]
            ]
        }
    }
}